SPCC/__init__.py
SPCC/prac1.py
SPCC/prac10.py
SPCC/prac11.py
SPCC/prac12.py
SPCC/prac13.py
SPCC/prac14.py
SPCC/prac16.py
SPCC/prac17.py
SPCC/prac2.py
SPCC/prac3.py
SPCC/prac4.py
SPCC/prac5.py
SPCC/prac6.py
SPCC/prac7.py
SPCC/prac8.py
SPCC/prac9.py
spcc-0.1.0.dist-info/METADATA
spcc-0.1.0.dist-info/WHEEL
spcc-0.1.0.dist-info/top_level.txt
spcc-0.1.0.dist-info/RECORD
