Metadata-Version: 2.4
Name: SPCC
Version: 0.1.0
Summary: A brief description of your package
Classifier: Programming Language :: Python :: 3
Classifier: License :: OSI Approved :: MIT License
Classifier: Operating System :: OS Independent
Dynamic: classifier
Dynamic: description-content-type
Dynamic: summary
